parosm/__init__.py
parosm/parse/__init__.py
parosm/parse/fileformat_pb2.py
parosm/parse/osmformat_pb2.py
parosm/parse/parsebase.py
parosm/parse/parsemulti.py
parosm/parse/parsepbf.py
parosm/parse/parsexml.py
parosm/prog/__init__.py
parosm/prog/osm2sql/__init__.py
parosm/prog/osminfo/__init__.py
parosm/types/__init__.py
parosm/types/node.py
parosm/types/osmtype.py
parosm/types/relation.py
parosm/types/way.py
parosm-0.2.dist-info/METADATA
parosm-0.2.dist-info/RECORD
parosm-0.2.dist-info/WHEEL
parosm-0.2.dist-info/entry_points.txt
parosm-0.2.dist-info/top_level.txt
