Metadata-Version: 2.1
Name: parosm
Version: 0.2
Summary: OpenStreetMap Parser
Home-page: https://github.com/DaGuich/parosm.git
License: GPL Version 3
Keywords: parser,osm,openstreetmap
Platform: UNKNOWN
Classifier: Programming Language :: Python :: 3
Requires-Python: >=3.0.0
Requires-Dist: protobuf
Requires-Dist: defusedxml (==0.5.0)
Requires-Dist: python-magic (==0.4.15)
